typing_to_configargparse/__init__.py
typing_to_configargparse-0.0.0rc0.dist-info/METADATA
typing_to_configargparse-0.0.0rc0.dist-info/WHEEL
typing_to_configargparse-0.0.0rc0.dist-info/top_level.txt
typing_to_configargparse-0.0.0rc0.dist-info/RECORD
