Metadata-Version: 2.1
Name: typing-to-configargparse
Version: 0.0.0rc0
Summary: Write once with inspection of python objects with type hinting from Python's standard library `typing` to generate a ConfigArgParser.
Home-page: https://github.com/prijatelj/typing-to-configargparse
Author: Derek S. Prijatelj
Author-email: dprijate@nd.edu
Classifier: Programming Language :: Python :: 3
Classifier: License :: OSI Approved :: MIT License
Classifier: Operating System :: OS Independent
Requires-Python: >=3.7
Requires-Dist: ConfigArgParse
Requires-Dist: PyYAML
